FunctionGUI/FunctionGUI.py
FunctionGUI/__init__.py
functiongui-0.7.0.dist-info/METADATA
functiongui-0.7.0.dist-info/WHEEL
functiongui-0.7.0.dist-info/top_level.txt
functiongui-0.7.0.dist-info/RECORD
