Metadata-Version: 2.4
Name: FunctionGUI
Version: 0.7.0
Summary: A simple Tkinter GUI library with basic widgets and functionality.
Home-page: https://github.com/aa425/FunctionGUI
Author: Aaroh Charne
Author-email: aaroh.charne@gmail.com
Classifier: Programming Language :: Python :: 3
Classifier: License :: OSI Approved :: MIT License
Classifier: Operating System :: OS Independent
Classifier: Development Status :: 3 - Alpha
Classifier: Intended Audience :: Developers
Classifier: Natural Language :: English
Classifier: Topic :: Software Development :: Libraries :: Python Modules
Requires-Python: >=3.6
Requires-Dist: Pillow
Requires-Dist: ttkbootstrap
Requires-Dist: tkinterdnd2
Requires-Dist: requests
Dynamic: author
Dynamic: author-email
Dynamic: classifier
Dynamic: description
Dynamic: description-content-type
Dynamic: home-page
Dynamic: requires-dist
Dynamic: requires-python
Dynamic: summary
